[{"html_filename":"buf-conn/docs/docs/BufConn.html","package":"buf-conn","namespace":"BufConn","name":"Overflow","typ":"Type","prefix":"","html_id":"BufConn.Overflow"},{"html_filename":"buf-conn/docs/docs/BufConn.html","package":"buf-conn","namespace":"BufConn","name":"BufConSt","typ":"Type -> Type","prefix":"record","html_id":"BufConn.BufConSt"},{"html_filename":"buf-conn/docs/docs/BufConn.html","package":"buf-conn","namespace":"BufConn","name":"MkBufConSt","typ":"Overflow -> queuedElem -> BufConSt queuedElem","prefix":"","html_id":"BufConn.MkBufConSt"},{"html_filename":"buf-conn/docs/docs/BufConn.html","package":"buf-conn","namespace":"BufConn","name":".overflow","typ":"BufConSt queuedElem -> Overflow","prefix":"","html_id":"BufConn.BufConSt.(.overflow)"},{"html_filename":"buf-conn/docs/docs/BufConn.html","package":"buf-conn","namespace":"BufConn","name":".queuedToSend","typ":"BufConSt queuedElem -> queuedElem","prefix":"","html_id":"BufConn.BufConSt.(.queuedToSend)"},{"html_filename":"buf-conn/docs/docs/BufConn.html","package":"buf-conn","namespace":"BufConn","name":"overflow","typ":"BufConSt queuedElem -> Overflow","prefix":"","html_id":"BufConn.BufConSt.overflow"},{"html_filename":"buf-conn/docs/docs/BufConn.html","package":"buf-conn","namespace":"BufConn","name":"queuedToSend","typ":"BufConSt queuedElem -> queuedElem","prefix":"","html_id":"BufConn.BufConSt.queuedToSend"},{"html_filename":"buf-conn/docs/docs/BufConn.html","package":"buf-conn","namespace":"BufConn","name":"DBufferedConn","typ":"Type -> Type -> Type -> Type -> Type -> Type","prefix":"","html_id":"BufConn.DBufferedConn"},{"html_filename":"buf-conn/docs/docs/BufConn.html","package":"buf-conn","namespace":"BufConn","name":"send","typ":"List Bits8 -> DBufferedConn r a () altOut altIn","prefix":"","html_id":"BufConn.send"},{"html_filename":"buf-conn/docs/docs/BufConn.html","package":"buf-conn","namespace":"BufConn","name":"result","typ":"r -> DBufferedConn r a b altOut altIn","prefix":"","html_id":"BufConn.result"},{"html_filename":"buf-conn/docs/docs/BufConn.html","package":"buf-conn","namespace":"BufConn","name":"sendAlt","typ":"b -> DBufferedConn r a rows rows b","prefix":"","html_id":"BufConn.sendAlt"},{"html_filename":"buf-conn/docs/docs/BufConn.html","package":"buf-conn","namespace":"BufConn","name":"read","typ":"(n : Nat) -> DBufferedConn r a (Vect n Bits8) altOut altIn","prefix":"","html_id":"BufConn.read"},{"html_filename":"buf-conn/docs/docs/BufConn.html","package":"buf-conn","namespace":"BufConn","name":"iteratorFromBufConn","typ":"BufConSt a -> DBufferedConn r a r altOut altIn -> DIterator (List Bits8) (List Bits8) altOut altIn r","prefix":"","html_id":"BufConn.iteratorFromBufConn"}]