[{"html_filename":"dependent-vect/docs/docs/Data.Vect.Dependent.html","package":"dependent-vect","namespace":"Data.Vect.Dependent","name":"DVect","typ":"(n : Nat) -> (Fin n -> Type) -> Type","prefix":"data","html_id":"Data.Vect.Dependent.DVect"},{"html_filename":"dependent-vect/docs/docs/Data.Vect.Dependent.html","package":"dependent-vect","namespace":"Data.Vect.Dependent","name":"Nil","typ":"DVect 0 ty","prefix":"","html_id":"Data.Vect.Dependent.Nil"},{"html_filename":"dependent-vect/docs/docs/Data.Vect.Dependent.html","package":"dependent-vect","namespace":"Data.Vect.Dependent","name":"(::)","typ":"ty FZ -> DVect n (ty . FS) -> DVect (S n) ty","prefix":"","html_id":"Data.Vect.Dependent.(::)"},{"html_filename":"dependent-vect/docs/docs/Data.Vect.Dependent.html","package":"dependent-vect","namespace":"Data.Vect.Dependent","name":"index","typ":"(i : Fin n) -> DVect n a -> a i","prefix":"","html_id":"Data.Vect.Dependent.index"},{"html_filename":"dependent-vect/docs/docs/Data.Vect.Dependent.html","package":"dependent-vect","namespace":"Data.Vect.Dependent","name":"tabulateI","typ":"((i : Fin n) -> a i) -> DVect n a","prefix":"","html_id":"Data.Vect.Dependent.tabulateI"},{"html_filename":"dependent-vect/docs/docs/Data.Vect.Dependent.html","package":"dependent-vect","namespace":"Data.Vect.Dependent","name":"tabulate","typ":"a i -> DVect n a","prefix":"","html_id":"Data.Vect.Dependent.tabulate"},{"html_filename":"dependent-vect/docs/docs/Data.Vect.Dependent.html","package":"dependent-vect","namespace":"Data.Vect.Dependent","name":"(++)","typ":"DVect n a -> DVect m b -> DVect (n + m) (either (Delay a) (Delay b) . splitSum)","prefix":"","html_id":"Data.Vect.Dependent.(++)"},{"html_filename":"dependent-vect/docs/docs/Data.Vect.Dependent.html","package":"dependent-vect","namespace":"Data.Vect.Dependent","name":"replaceAt","typ":"(i : Fin n) -> a i -> DVect n a -> DVect n a","prefix":"","html_id":"Data.Vect.Dependent.replaceAt"},{"html_filename":"dependent-vect/docs/docs/Data.Vect.Dependent.html","package":"dependent-vect","namespace":"Data.Vect.Dependent","name":"updateAt","typ":"(i : Fin n) -> (a i -> a i) -> DVect n a -> DVect n a","prefix":"","html_id":"Data.Vect.Dependent.updateAt"},{"html_filename":"dependent-vect/docs/docs/Data.Vect.Dependent.html","package":"dependent-vect","namespace":"Data.Vect.Dependent","name":"mapI","typ":"((i : Fin n) -> a i -> b i) -> DVect n a -> DVect n b","prefix":"","html_id":"Data.Vect.Dependent.mapI"},{"html_filename":"dependent-vect/docs/docs/Data.Vect.Dependent.html","package":"dependent-vect","namespace":"Data.Vect.Dependent","name":"map","typ":"(a i -> b i) -> DVect n a -> DVect n b","prefix":"","html_id":"Data.Vect.Dependent.map"},{"html_filename":"dependent-vect/docs/docs/Data.Vect.Dependent.html","package":"dependent-vect","namespace":"Data.Vect.Dependent","name":"(<$>)","typ":"(a i -> b i) -> DVect n a -> DVect n b","prefix":"","html_id":"Data.Vect.Dependent.(<$>)"},{"html_filename":"dependent-vect/docs/docs/Data.Vect.Dependent.html","package":"dependent-vect","namespace":"Data.Vect.Dependent","name":"(<&>)","typ":"DVect n a -> (a i -> b i) -> DVect n b","prefix":"","html_id":"Data.Vect.Dependent.(<&>)"},{"html_filename":"dependent-vect/docs/docs/Data.Vect.Dependent.html","package":"dependent-vect","namespace":"Data.Vect.Dependent","name":"mapPreI","typ":"((i : Fin n) -> DVect (finToNat i) (b . weakenToSuper) -> a i -> b i) -> DVect n a -> DVect n b","prefix":"","html_id":"Data.Vect.Dependent.mapPreI"},{"html_filename":"dependent-vect/docs/docs/Data.Vect.Dependent.html","package":"dependent-vect","namespace":"Data.Vect.Dependent","name":"mapPre","typ":"(DVect (finToNat i) (b . weakenToSuper) -> a i -> b i) -> DVect n a -> DVect n b","prefix":"","html_id":"Data.Vect.Dependent.mapPre"},{"html_filename":"dependent-vect/docs/docs/Data.Vect.Dependent.html","package":"dependent-vect","namespace":"Data.Vect.Dependent","name":"downmapI","typ":"((i : Fin n) -> a i -> b) -> DVect n a -> Vect n b","prefix":"","html_id":"Data.Vect.Dependent.downmapI"},{"html_filename":"dependent-vect/docs/docs/Data.Vect.Dependent.html","package":"dependent-vect","namespace":"Data.Vect.Dependent","name":"downmap","typ":"(a i -> b) -> DVect n a -> Vect n b","prefix":"","html_id":"Data.Vect.Dependent.downmap"},{"html_filename":"dependent-vect/docs/docs/Data.Vect.Dependent.html","package":"dependent-vect","namespace":"Data.Vect.Dependent","name":"upmapI","typ":"((i : Fin n) -> a -> b i) -> Vect n a -> DVect n b","prefix":"","html_id":"Data.Vect.Dependent.upmapI"},{"html_filename":"dependent-vect/docs/docs/Data.Vect.Dependent.html","package":"dependent-vect","namespace":"Data.Vect.Dependent","name":"upmap","typ":"(a -> b i) -> Vect n a -> DVect n b","prefix":"","html_id":"Data.Vect.Dependent.upmap"},{"html_filename":"dependent-vect/docs/docs/Data.Vect.Dependent.html","package":"dependent-vect","namespace":"Data.Vect.Dependent","name":"zip","typ":"DVect n a -> DVect n b -> DVect n (\\i => (a i, b i))","prefix":"","html_id":"Data.Vect.Dependent.zip"},{"html_filename":"dependent-vect/docs/docs/Data.Vect.Dependent.html","package":"dependent-vect","namespace":"Data.Vect.Dependent","name":"zipWithI","typ":"((i : Fin n) -> a i -> b i -> c i) -> DVect n a -> DVect n b -> DVect n c","prefix":"","html_id":"Data.Vect.Dependent.zipWithI"},{"html_filename":"dependent-vect/docs/docs/Data.Vect.Dependent.html","package":"dependent-vect","namespace":"Data.Vect.Dependent","name":"zipWith","typ":"(a i -> b i -> c i) -> DVect n a -> DVect n b -> DVect n c","prefix":"","html_id":"Data.Vect.Dependent.zipWith"},{"html_filename":"dependent-vect/docs/docs/Data.Vect.Dependent.html","package":"dependent-vect","namespace":"Data.Vect.Dependent","name":"(<*>)","typ":"DVect n (\\i => a i -> b i) -> DVect n a -> DVect n b","prefix":"","html_id":"Data.Vect.Dependent.(<*>)"},{"html_filename":"dependent-vect/docs/docs/Data.Vect.Dependent.html","package":"dependent-vect","namespace":"Data.Vect.Dependent","name":"transpose","typ":"{0 a : Fin n -> Fin m -> Type} -> DVect n (\\i => DVect m (\\j => a i j)) -> DVect m (\\j => DVect n (\\i => a i j))","prefix":"","html_id":"Data.Vect.Dependent.transpose"},{"html_filename":"dependent-vect/docs/docs/Data.Vect.Dependent.html","package":"dependent-vect","namespace":"Data.Vect.Dependent","name":"foldlI","typ":"((i : Fin n) -> acc -> a i -> acc) -> acc -> DVect n a -> acc","prefix":"","html_id":"Data.Vect.Dependent.foldlI"},{"html_filename":"dependent-vect/docs/docs/Data.Vect.Dependent.html","package":"dependent-vect","namespace":"Data.Vect.Dependent","name":"foldl","typ":"(acc -> a i -> acc) -> acc -> DVect n a -> acc","prefix":"","html_id":"Data.Vect.Dependent.foldl"},{"html_filename":"dependent-vect/docs/docs/Data.Vect.Dependent.html","package":"dependent-vect","namespace":"Data.Vect.Dependent","name":"foldrI","typ":"((i : Fin n) -> a i -> Lazy acc -> acc) -> acc -> DVect n a -> acc","prefix":"","html_id":"Data.Vect.Dependent.foldrI"},{"html_filename":"dependent-vect/docs/docs/Data.Vect.Dependent.html","package":"dependent-vect","namespace":"Data.Vect.Dependent","name":"foldr","typ":"(a i -> Lazy acc -> acc) -> acc -> DVect n a -> acc","prefix":"","html_id":"Data.Vect.Dependent.foldr"},{"html_filename":"dependent-vect/docs/docs/Data.Vect.Dependent.html","package":"dependent-vect","namespace":"Data.Vect.Dependent","name":"foldlMI","typ":"Monad m => ((i : Fin n) -> acc -> a i -> m acc) -> acc -> DVect n a -> m acc","prefix":"","html_id":"Data.Vect.Dependent.foldlMI"},{"html_filename":"dependent-vect/docs/docs/Data.Vect.Dependent.html","package":"dependent-vect","namespace":"Data.Vect.Dependent","name":"foldlM","typ":"Monad m => (acc -> a i -> m acc) -> acc -> DVect n a -> m acc","prefix":"","html_id":"Data.Vect.Dependent.foldlM"},{"html_filename":"dependent-vect/docs/docs/Data.Vect.Dependent.html","package":"dependent-vect","namespace":"Data.Vect.Dependent","name":"traverseI","typ":"Applicative f => ((i : Fin n) -> a i -> f (b i)) -> DVect n a -> f (DVect n b)","prefix":"","html_id":"Data.Vect.Dependent.traverseI"},{"html_filename":"dependent-vect/docs/docs/Data.Vect.Dependent.html","package":"dependent-vect","namespace":"Data.Vect.Dependent","name":"traverse","typ":"Applicative f => (a i -> f (b i)) -> DVect n a -> f (DVect n b)","prefix":"","html_id":"Data.Vect.Dependent.traverse"},{"html_filename":"dependent-vect/docs/docs/Data.Vect.Dependent.html","package":"dependent-vect","namespace":"Data.Vect.Dependent","name":"sequence","typ":"Applicative f => DVect n (f . a) -> f (DVect n a)","prefix":"","html_id":"Data.Vect.Dependent.sequence"},{"html_filename":"dependent-vect/docs/docs/Data.Vect.Dependent.html","package":"dependent-vect","namespace":"Data.Vect.Dependent","name":"forI","typ":"Applicative f => DVect n a -> ((i : Fin n) -> a i -> f (b i)) -> f (DVect n b)","prefix":"","html_id":"Data.Vect.Dependent.forI"},{"html_filename":"dependent-vect/docs/docs/Data.Vect.Dependent.html","package":"dependent-vect","namespace":"Data.Vect.Dependent","name":"for","typ":"Applicative f => DVect n a -> (a i -> f (b i)) -> f (DVect n b)","prefix":"","html_id":"Data.Vect.Dependent.for"}]