[{"html_filename":"parser-tsv/docs/docs/Derive.TSV.Encoder.html","package":"parser-tsv","namespace":"Derive.TSV.Encoder","name":"encClaim","typ":"Visibility -> Name -> ParamTypeInfo -> Decl","prefix":"","html_id":"Derive.TSV.Encoder.encClaim"},{"html_filename":"parser-tsv/docs/docs/Derive.TSV.Encoder.html","package":"parser-tsv","namespace":"Derive.TSV.Encoder","name":"encoderImplClaim","typ":"Visibility -> Name -> ParamTypeInfo -> Decl","prefix":"","html_id":"Derive.TSV.Encoder.encoderImplClaim"},{"html_filename":"parser-tsv/docs/docs/Derive.TSV.Encoder.html","package":"parser-tsv","namespace":"Derive.TSV.Encoder","name":"encoderImplDef","typ":"Name -> Name -> Decl","prefix":"","html_id":"Derive.TSV.Encoder.encoderImplDef"},{"html_filename":"parser-tsv/docs/docs/Derive.TSV.Encoder.html","package":"parser-tsv","namespace":"Derive.TSV.Encoder","name":"encDef","typ":"Name -> Con n vs -> Decl","prefix":"","html_id":"Derive.TSV.Encoder.encDef"},{"html_filename":"parser-tsv/docs/docs/Derive.TSV.Encoder.html","package":"parser-tsv","namespace":"Derive.TSV.Encoder","name":"enumDef","typ":"Name -> ParamTypeInfo -> Decl","prefix":"","html_id":"Derive.TSV.Encoder.enumDef"},{"html_filename":"parser-tsv/docs/docs/Derive.TSV.Encoder.html","package":"parser-tsv","namespace":"Derive.TSV.Encoder","name":"TSVEncoderVis","typ":"Visibility -> List Name -> ParamTypeInfo -> Res (List TopLevel)","prefix":"","html_id":"Derive.TSV.Encoder.TSVEncoderVis"},{"html_filename":"parser-tsv/docs/docs/Derive.TSV.Encoder.html","package":"parser-tsv","namespace":"Derive.TSV.Encoder","name":"TSVEncoder","typ":"List Name -> ParamTypeInfo -> Res (List TopLevel)","prefix":"","html_id":"Derive.TSV.Encoder.TSVEncoder"},{"html_filename":"parser-tsv/docs/docs/Text.TSV.Encoder.html","package":"parser-tsv","namespace":"Text.TSV.Encoder","name":"TSVEncoder","typ":"Type -> Type","prefix":"interface","html_id":"Text.TSV.Encoder.TSVEncoder"},{"html_filename":"parser-tsv/docs/docs/Text.TSV.Encoder.html","package":"parser-tsv","namespace":"Text.TSV.Encoder","name":"encodeOnto","typ":"SnocList String -> a -> SnocList String","prefix":"","html_id":"Text.TSV.Encoder.encodeOnto"},{"html_filename":"parser-tsv/docs/docs/Text.TSV.Encoder.html","package":"parser-tsv","namespace":"Text.TSV.Encoder","name":"toRow","typ":"TSVEncoder a => a -> String","prefix":"","html_id":"Text.TSV.Encoder.toRow"},{"html_filename":"parser-tsv/docs/docs/Text.TSV.Encoder.html","package":"parser-tsv","namespace":"Text.TSV.Encoder","name":"toTable","typ":"TSVEncoder a => List a -> String","prefix":"","html_id":"Text.TSV.Encoder.toTable"},{"html_filename":"parser-tsv/docs/docs/Derive.TSV.Decoder.html","package":"parser-tsv","namespace":"Derive.TSV.Decoder","name":"decClaim","typ":"Visibility -> Name -> ParamTypeInfo -> Decl","prefix":"","html_id":"Derive.TSV.Decoder.decClaim"},{"html_filename":"parser-tsv/docs/docs/Derive.TSV.Decoder.html","package":"parser-tsv","namespace":"Derive.TSV.Decoder","name":"decoderImplClaim","typ":"Visibility -> Name -> ParamTypeInfo -> Decl","prefix":"","html_id":"Derive.TSV.Decoder.decoderImplClaim"},{"html_filename":"parser-tsv/docs/docs/Derive.TSV.Decoder.html","package":"parser-tsv","namespace":"Derive.TSV.Decoder","name":"decoderImplDef","typ":"Name -> Name -> Decl","prefix":"","html_id":"Derive.TSV.Decoder.decoderImplDef"},{"html_filename":"parser-tsv/docs/docs/Derive.TSV.Decoder.html","package":"parser-tsv","namespace":"Derive.TSV.Decoder","name":"TSVDecoderVis","typ":"Visibility -> List Name -> ParamTypeInfo -> Res (List TopLevel)","prefix":"","html_id":"Derive.TSV.Decoder.TSVDecoderVis"},{"html_filename":"parser-tsv/docs/docs/Derive.TSV.Decoder.html","package":"parser-tsv","namespace":"Derive.TSV.Decoder","name":"TSVDecoder","typ":"List Name -> ParamTypeInfo -> Res (List TopLevel)","prefix":"","html_id":"Derive.TSV.Decoder.TSVDecoder"},{"html_filename":"parser-tsv/docs/docs/Text.TSV.Decoder.html","package":"parser-tsv","namespace":"Text.TSV.Decoder","name":"TSVDecoder","typ":"Type -> Type","prefix":"interface","html_id":"Text.TSV.Decoder.TSVDecoder"},{"html_filename":"parser-tsv/docs/docs/Text.TSV.Decoder.html","package":"parser-tsv","namespace":"Text.TSV.Decoder","name":"decodeFrom","typ":"Tok False e a","prefix":"","html_id":"Text.TSV.Decoder.decodeFrom"},{"html_filename":"parser-tsv/docs/docs/Text.TSV.Decoder.html","package":"parser-tsv","namespace":"Text.TSV.Decoder","name":"str","typ":"Tok False e String","prefix":"","html_id":"Text.TSV.Decoder.str"},{"html_filename":"parser-tsv/docs/docs/Text.TSV.Decoder.html","package":"parser-tsv","namespace":"Text.TSV.Decoder","name":"refine","typ":"Tok b1 e a -> (a -> Maybe b) -> Tok False e b","prefix":"","html_id":"Text.TSV.Decoder.refine"},{"html_filename":"parser-tsv/docs/docs/Text.TSV.Decoder.html","package":"parser-tsv","namespace":"Text.TSV.Decoder","name":"refineNum","typ":"Tok b1 e a -> (a -> Maybe b) -> Tok False e b","prefix":"","html_id":"Text.TSV.Decoder.refineNum"},{"html_filename":"parser-tsv/docs/docs/Text.TSV.Decoder.html","package":"parser-tsv","namespace":"Text.TSV.Decoder","name":"natural","typ":"(Nat -> Maybe a) -> Tok False e a","prefix":"","html_id":"Text.TSV.Decoder.natural"},{"html_filename":"parser-tsv/docs/docs/Text.TSV.Decoder.html","package":"parser-tsv","namespace":"Text.TSV.Decoder","name":"boundedNat","typ":"Cast Nat a => Nat -> Tok False e a","prefix":"","html_id":"Text.TSV.Decoder.boundedNat"},{"html_filename":"parser-tsv/docs/docs/Text.TSV.Decoder.html","package":"parser-tsv","namespace":"Text.TSV.Decoder","name":"integral","typ":"(Integer -> Maybe a) -> Tok False e a","prefix":"","html_id":"Text.TSV.Decoder.integral"},{"html_filename":"parser-tsv/docs/docs/Text.TSV.Decoder.html","package":"parser-tsv","namespace":"Text.TSV.Decoder","name":"boundedInt","typ":"Cast Integer a => Integer -> Integer -> Tok False e a","prefix":"","html_id":"Text.TSV.Decoder.boundedInt"},{"html_filename":"parser-tsv/docs/docs/Text.TSV.Decoder.html","package":"parser-tsv","namespace":"Text.TSV.Decoder","name":"float","typ":"(Double -> Maybe a) -> Tok False e a","prefix":"","html_id":"Text.TSV.Decoder.float"},{"html_filename":"parser-tsv/docs/docs/Text.TSV.Decoder.html","package":"parser-tsv","namespace":"Text.TSV.Decoder","name":"tab","typ":"Tok False e ()","prefix":"","html_id":"Text.TSV.Decoder.tab"},{"html_filename":"parser-tsv/docs/docs/Text.TSV.Decoder.html","package":"parser-tsv","namespace":"Text.TSV.Decoder","name":"readTable","typ":"TSVDecoder a => Origin -> String -> Either (FileContext, ParseError Void e) (List a)","prefix":"","html_id":"Text.TSV.Decoder.readTable"}]