[{"html_filename":"pg-idris/docs/docs/Postgres.DB.html","package":"pg-idris","namespace":"Postgres.DB","name":"withConn","typ":"HasIO io => String -> (Conn -> io b) -> (ConnectionStatus -> io b) -> io b","prefix":"","html_id":"Postgres.DB.withConn"},{"html_filename":"pg-idris/docs/docs/Postgres.DB.html","package":"pg-idris","namespace":"Postgres.DB","name":"DBState","typ":"Type","prefix":"data","html_id":"Postgres.DB.DBState"},{"html_filename":"pg-idris/docs/docs/Postgres.DB.html","package":"pg-idris","namespace":"Postgres.DB","name":"Open","typ":"DBState","prefix":"","html_id":"Postgres.DB.Open"},{"html_filename":"pg-idris/docs/docs/Postgres.DB.html","package":"pg-idris","namespace":"Postgres.DB","name":"Closed","typ":"DBState","prefix":"","html_id":"Postgres.DB.Closed"},{"html_filename":"pg-idris/docs/docs/Postgres.DB.html","package":"pg-idris","namespace":"Postgres.DB","name":"OpenResult","typ":"Type","prefix":"data","html_id":"Postgres.DB.OpenResult"},{"html_filename":"pg-idris/docs/docs/Postgres.DB.html","package":"pg-idris","namespace":"Postgres.DB","name":"OK","typ":"OpenResult","prefix":"","html_id":"Postgres.DB.OK"},{"html_filename":"pg-idris/docs/docs/Postgres.DB.html","package":"pg-idris","namespace":"Postgres.DB","name":"Failed","typ":"String -> OpenResult","prefix":"","html_id":"Postgres.DB.Failed"},{"html_filename":"pg-idris/docs/docs/Postgres.DB.html","package":"pg-idris","namespace":"Postgres.DB","name":"OpenResultState","typ":"OpenResult -> DBState","prefix":"","html_id":"Postgres.DB.OpenResultState"},{"html_filename":"pg-idris/docs/docs/Postgres.DB.html","package":"pg-idris","namespace":"Postgres.DB","name":"Connection","typ":"Type","prefix":"data","html_id":"Postgres.DB.Connection"},{"html_filename":"pg-idris/docs/docs/Postgres.DB.html","package":"pg-idris","namespace":"Postgres.DB","name":"MkConnection","typ":"Conn -> TypeDictionary -> Connection","prefix":"","html_id":"Postgres.DB.MkConnection"},{"html_filename":"pg-idris/docs/docs/Postgres.DB.html","package":"pg-idris","namespace":"Postgres.DB","name":"Database","typ":"(ty : Type) -> DBState -> (ty -> DBState) -> Type","prefix":"data","html_id":"Postgres.DB.Database"},{"html_filename":"pg-idris/docs/docs/Postgres.DB.html","package":"pg-idris","namespace":"Postgres.DB","name":"DBOpen","typ":"String -> Database OpenResult Closed OpenResultState","prefix":"","html_id":"Postgres.DB.DBOpen"},{"html_filename":"pg-idris/docs/docs/Postgres.DB.html","package":"pg-idris","namespace":"Postgres.DB","name":"DBClose","typ":"Database () Open (const Closed)","prefix":"","html_id":"Postgres.DB.DBClose"},{"html_filename":"pg-idris/docs/docs/Postgres.DB.html","package":"pg-idris","namespace":"Postgres.DB","name":"Exec","typ":"(Connection -> IO a) -> Database a Open (const Open)","prefix":"","html_id":"Postgres.DB.Exec"},{"html_filename":"pg-idris/docs/docs/Postgres.DB.html","package":"pg-idris","namespace":"Postgres.DB","name":"DIO","typ":"IO a -> Database a s1 (const s1)","prefix":"","html_id":"Postgres.DB.DIO"},{"html_filename":"pg-idris/docs/docs/Postgres.DB.html","package":"pg-idris","namespace":"Postgres.DB","name":"GetTypes","typ":"Database TypeDictionary Open (const Open)","prefix":"","html_id":"Postgres.DB.GetTypes"},{"html_filename":"pg-idris/docs/docs/Postgres.DB.html","package":"pg-idris","namespace":"Postgres.DB","name":"Pure","typ":"(x : a) -> Database a (stateFn x) stateFn","prefix":"","html_id":"Postgres.DB.Pure"},{"html_filename":"pg-idris/docs/docs/Postgres.DB.html","package":"pg-idris","namespace":"Postgres.DB","name":"Bind","typ":"Database a s1 s2Fn -> ((x : a) -> Database b (s2Fn x) s3Fn) -> Database b s1 s3Fn","prefix":"","html_id":"Postgres.DB.Bind"},{"html_filename":"pg-idris/docs/docs/Postgres.DB.html","package":"pg-idris","namespace":"Postgres.DB","name":"liftIO'","typ":"IO a -> Database a s1 (const s1)","prefix":"","html_id":"Postgres.DB.liftIO'"},{"html_filename":"pg-idris/docs/docs/Postgres.DB.html","package":"pg-idris","namespace":"Postgres.DB","name":"evalDatabase","typ":"HasIO io => Database a Closed (const Closed) -> io a","prefix":"","html_id":"Postgres.DB.evalDatabase"},{"html_filename":"pg-idris/docs/docs/Postgres.DB.html","package":"pg-idris","namespace":"Postgres.DB","name":"initDatabase","typ":"Database () Closed (const Closed)","prefix":"","html_id":"Postgres.DB.initDatabase"},{"html_filename":"pg-idris/docs/docs/Postgres.DB.html","package":"pg-idris","namespace":"Postgres.DB","name":"openDatabase","typ":"String -> Database OpenResult Closed OpenResultState","prefix":"","html_id":"Postgres.DB.openDatabase"},{"html_filename":"pg-idris/docs/docs/Postgres.DB.html","package":"pg-idris","namespace":"Postgres.DB","name":"closeDatabase","typ":"Database () Open (const Closed)","prefix":"","html_id":"Postgres.DB.closeDatabase"},{"html_filename":"pg-idris/docs/docs/Postgres.DB.html","package":"pg-idris","namespace":"Postgres.DB","name":"exec","typ":"(Connection -> IO a) -> Database a Open (const Open)","prefix":"","html_id":"Postgres.DB.exec"},{"html_filename":"pg-idris/docs/docs/Postgres.DB.html","package":"pg-idris","namespace":"Postgres.DB","name":"unsafeExec","typ":"(Conn -> IO a) -> Database a Open (const Open)","prefix":"","html_id":"Postgres.DB.unsafeExec"},{"html_filename":"pg-idris/docs/docs/Postgres.DB.html","package":"pg-idris","namespace":"Postgres.DB","name":"withDB","typ":"HasIO io => String -> Database a Open (const Open) -> io (Either String a)","prefix":"","html_id":"Postgres.DB.withDB"},{"html_filename":"pg-idris/docs/docs/Postgres.DB.html","package":"pg-idris","namespace":"Postgres.DB","name":"debugDumpTypes","typ":"Database () Open (const Open)","prefix":"","html_id":"Postgres.DB.debugDumpTypes"},{"html_filename":"pg-idris/docs/docs/Postgres.DB.html","package":"pg-idris","namespace":"Postgres.DB","name":"stringQuery","typ":"(header : Bool) -> String -> Connection -> IO (Either String (StringResultset header))","prefix":"","html_id":"Postgres.DB.stringQuery"},{"html_filename":"pg-idris/docs/docs/Postgres.DB.html","package":"pg-idris","namespace":"Postgres.DB","name":"jsonQuery","typ":"String -> Connection -> IO (Maybe JSON)","prefix":"","html_id":"Postgres.DB.jsonQuery"},{"html_filename":"pg-idris/docs/docs/Postgres.DB.html","package":"pg-idris","namespace":"Postgres.DB","name":"expectedQuery","typ":"(expected : Vect cols Type) -> String -> All Castable expected => Connection -> IO (Either String (rowCount : Nat ** Vect rowCount (HVect expected)))","prefix":"","html_id":"Postgres.DB.expectedQuery"},{"html_filename":"pg-idris/docs/docs/Postgres.DB.html","package":"pg-idris","namespace":"Postgres.DB","name":"tableQuery","typ":"{auto {conArg:2942} : PostgresTable t} -> (table : t) -> (cols : Vect n (ColumnIdentifier, Type)) -> HasMappings IdrCast table cols => Connection -> IO (Either String (rowCount : Nat ** Vect rowCount (HVect (snd <$> cols))))","prefix":"","html_id":"Postgres.DB.tableQuery"},{"html_filename":"pg-idris/docs/docs/Postgres.DB.html","package":"pg-idris","namespace":"Postgres.DB","name":"tableQuery'","typ":"{auto {conArg:3028} : PostgresTable t} -> (table : t) -> (cols : Vect n (String, Type)) -> HasMappings IdrCast table (mapFst (MkColumnId (aliasOrName table)) <$> cols) => Connection -> IO (Either String (rowCount : Nat ** Vect rowCount (HVect (snd <$> (mapFst (MkColumnId (aliasOrName table)) <$> cols)))))","prefix":"","html_id":"Postgres.DB.StringColumns.tableQuery'"},{"html_filename":"pg-idris/docs/docs/Postgres.DB.html","package":"pg-idris","namespace":"Postgres.DB","name":"perform","typ":"String -> Connection -> IO ResultStatus","prefix":"","html_id":"Postgres.DB.perform"},{"html_filename":"pg-idris/docs/docs/Postgres.DB.html","package":"pg-idris","namespace":"Postgres.DB","name":"tableInsert","typ":"(table : PersistedTable) -> (cols : Vect n ColumnIdentifier) -> HVect colTypes -> HasLooseMappings PGCast table (cols `zip` colTypes) => Connection -> IO ResultStatus","prefix":"","html_id":"Postgres.DB.tableInsert"},{"html_filename":"pg-idris/docs/docs/Postgres.DB.html","package":"pg-idris","namespace":"Postgres.DB","name":"listen","typ":"String -> Connection -> IO ResultStatus","prefix":"","html_id":"Postgres.DB.listen"},{"html_filename":"pg-idris/docs/docs/Postgres.DB.html","package":"pg-idris","namespace":"Postgres.DB","name":"nextNotification","typ":"Connection -> IO (Maybe Notification)","prefix":"","html_id":"Postgres.DB.nextNotification"},{"html_filename":"pg-idris/docs/docs/Postgres.DB.html","package":"pg-idris","namespace":"Postgres.DB","name":"notificationStream","typ":"Connection -> Stream (IO Notification)","prefix":"","html_id":"Postgres.DB.notificationStream"},{"html_filename":"pg-idris/docs/docs/Postgres.Exec.html","package":"pg-idris","namespace":"Postgres.Exec","name":"withExecResult","typ":"Conn -> String -> (Result -> IO b) -> IO b","prefix":"","html_id":"Postgres.Exec.withExecResult"},{"html_filename":"pg-idris/docs/docs/Postgres.Exec.html","package":"pg-idris","namespace":"Postgres.Exec","name":"ignore","typ":"Result -> IO ()","prefix":"","html_id":"Postgres.Exec.ignore"},{"html_filename":"pg-idris/docs/docs/Postgres.Data.PostgresType.html","package":"pg-idris","namespace":"Postgres.Data.PostgresType","name":"Oid","typ":"Type","prefix":"data","html_id":"Postgres.Data.PostgresType.Oid"},{"html_filename":"pg-idris/docs/docs/Postgres.Data.PostgresType.html","package":"pg-idris","namespace":"Postgres.Data.PostgresType","name":"MkOid","typ":"Int -> Oid","prefix":"","html_id":"Postgres.Data.PostgresType.MkOid"},{"html_filename":"pg-idris/docs/docs/Postgres.Data.PostgresType.html","package":"pg-idris","namespace":"Postgres.Data.PostgresType","name":"oidToInt","typ":"Oid -> Int","prefix":"","html_id":"Postgres.Data.PostgresType.oidToInt"},{"html_filename":"pg-idris/docs/docs/Postgres.Data.PostgresType.html","package":"pg-idris","namespace":"Postgres.Data.PostgresType","name":"PType","typ":"Type","prefix":"data","html_id":"Postgres.Data.PostgresType.PType"},{"html_filename":"pg-idris/docs/docs/Postgres.Data.PostgresType.html","package":"pg-idris","namespace":"Postgres.Data.PostgresType","name":"PInteger","typ":"PType","prefix":"","html_id":"Postgres.Data.PostgresType.PInteger"},{"html_filename":"pg-idris/docs/docs/Postgres.Data.PostgresType.html","package":"pg-idris","namespace":"Postgres.Data.PostgresType","name":"PDouble","typ":"PType","prefix":"","html_id":"Postgres.Data.PostgresType.PDouble"},{"html_filename":"pg-idris/docs/docs/Postgres.Data.PostgresType.html","package":"pg-idris","namespace":"Postgres.Data.PostgresType","name":"PChar","typ":"PType","prefix":"","html_id":"Postgres.Data.PostgresType.PChar"},{"html_filename":"pg-idris/docs/docs/Postgres.Data.PostgresType.html","package":"pg-idris","namespace":"Postgres.Data.PostgresType","name":"PBoolean","typ":"PType","prefix":"","html_id":"Postgres.Data.PostgresType.PBoolean"},{"html_filename":"pg-idris/docs/docs/Postgres.Data.PostgresType.html","package":"pg-idris","namespace":"Postgres.Data.PostgresType","name":"PDate","typ":"PType","prefix":"","html_id":"Postgres.Data.PostgresType.PDate"},{"html_filename":"pg-idris/docs/docs/Postgres.Data.PostgresType.html","package":"pg-idris","namespace":"Postgres.Data.PostgresType","name":"PTime","typ":"PType","prefix":"","html_id":"Postgres.Data.PostgresType.PTime"},{"html_filename":"pg-idris/docs/docs/Postgres.Data.PostgresType.html","package":"pg-idris","namespace":"Postgres.Data.PostgresType","name":"PDatetime","typ":"PType","prefix":"","html_id":"Postgres.Data.PostgresType.PDatetime"},{"html_filename":"pg-idris/docs/docs/Postgres.Data.PostgresType.html","package":"pg-idris","namespace":"Postgres.Data.PostgresType","name":"PString","typ":"PType","prefix":"","html_id":"Postgres.Data.PostgresType.PString"},{"html_filename":"pg-idris/docs/docs/Postgres.Data.PostgresType.html","package":"pg-idris","namespace":"Postgres.Data.PostgresType","name":"PJson","typ":"PType","prefix":"","html_id":"Postgres.Data.PostgresType.PJson"},{"html_filename":"pg-idris/docs/docs/Postgres.Data.PostgresType.html","package":"pg-idris","namespace":"Postgres.Data.PostgresType","name":"PUuid","typ":"PType","prefix":"","html_id":"Postgres.Data.PostgresType.PUuid"},{"html_filename":"pg-idris/docs/docs/Postgres.Data.PostgresType.html","package":"pg-idris","namespace":"Postgres.Data.PostgresType","name":"POid","typ":"PType","prefix":"","html_id":"Postgres.Data.PostgresType.POid"},{"html_filename":"pg-idris/docs/docs/Postgres.Data.PostgresType.html","package":"pg-idris","namespace":"Postgres.Data.PostgresType","name":"PArray","typ":"PType -> PType","prefix":"","html_id":"Postgres.Data.PostgresType.PArray"},{"html_filename":"pg-idris/docs/docs/Postgres.Data.PostgresType.html","package":"pg-idris","namespace":"Postgres.Data.PostgresType","name":"POther","typ":"String -> PType","prefix":"","html_id":"Postgres.Data.PostgresType.POther"},{"html_filename":"pg-idris/docs/docs/Postgres.Data.PostgresType.html","package":"pg-idris","namespace":"Postgres.Data.PostgresType","name":"PUnknown","typ":"Oid -> PType","prefix":"","html_id":"Postgres.Data.PostgresType.PUnknown"},{"html_filename":"pg-idris/docs/docs/Postgres.Data.PostgresType.html","package":"pg-idris","namespace":"Postgres.Data.PostgresType","name":"Nullability","typ":"Type","prefix":"data","html_id":"Postgres.Data.PostgresType.Nullability"},{"html_filename":"pg-idris/docs/docs/Postgres.Data.PostgresType.html","package":"pg-idris","namespace":"Postgres.Data.PostgresType","name":"Nullable","typ":"Nullability","prefix":"","html_id":"Postgres.Data.PostgresType.Nullable"},{"html_filename":"pg-idris/docs/docs/Postgres.Data.PostgresType.html","package":"pg-idris","namespace":"Postgres.Data.PostgresType","name":"NonNullable","typ":"Nullability","prefix":"","html_id":"Postgres.Data.PostgresType.NonNullable"},{"html_filename":"pg-idris/docs/docs/Postgres.Data.PostgresType.html","package":"pg-idris","namespace":"Postgres.Data.PostgresType","name":"PColType","typ":"PType -> Type","prefix":"data","html_id":"Postgres.Data.PostgresType.PColType"},{"html_filename":"pg-idris/docs/docs/Postgres.Data.PostgresType.html","package":"pg-idris","namespace":"Postgres.Data.PostgresType","name":"MkColType","typ":"Nullability -> (pt : PType) -> PColType pt","prefix":"","html_id":"Postgres.Data.PostgresType.MkColType"},{"html_filename":"pg-idris/docs/docs/Postgres.Data.PostgresType.html","package":"pg-idris","namespace":"Postgres.Data.PostgresType","name":"pType","typ":"PColType t -> PType","prefix":"","html_id":"Postgres.Data.PostgresType.pType"},{"html_filename":"pg-idris/docs/docs/Postgres.Data.PostgresType.html","package":"pg-idris","namespace":"Postgres.Data.PostgresType","name":"nullable","typ":"PColType t -> Bool","prefix":"","html_id":"Postgres.Data.PostgresType.nullable"},{"html_filename":"pg-idris/docs/docs/Postgres.Data.PostgresType.html","package":"pg-idris","namespace":"Postgres.Data.PostgresType","name":"makeNullable","typ":"PColType t -> PColType t","prefix":"","html_id":"Postgres.Data.PostgresType.makeNullable"},{"html_filename":"pg-idris/docs/docs/Postgres.Data.PostgresType.html","package":"pg-idris","namespace":"Postgres.Data.PostgresType","name":"FormatCode","typ":"Type","prefix":"data","html_id":"Postgres.Data.PostgresType.FormatCode"},{"html_filename":"pg-idris/docs/docs/Postgres.Data.PostgresType.html","package":"pg-idris","namespace":"Postgres.Data.PostgresType","name":"Text","typ":"FormatCode","prefix":"","html_id":"Postgres.Data.PostgresType.Text"},{"html_filename":"pg-idris/docs/docs/Postgres.Data.PostgresType.html","package":"pg-idris","namespace":"Postgres.Data.PostgresType","name":"Binary","typ":"FormatCode","prefix":"","html_id":"Postgres.Data.PostgresType.Binary"},{"html_filename":"pg-idris/docs/docs/Postgres.Data.PostgresType.html","package":"pg-idris","namespace":"Postgres.Data.PostgresType","name":"TypeDictionary","typ":"Type","prefix":"data","html_id":"Postgres.Data.PostgresType.TypeDictionary"},{"html_filename":"pg-idris/docs/docs/Postgres.Data.PostgresType.html","package":"pg-idris","namespace":"Postgres.Data.PostgresType","name":"MkTypeDictionary","typ":"List (Oid, PType) -> TypeDictionary","prefix":"","html_id":"Postgres.Data.PostgresType.MkTypeDictionary"},{"html_filename":"pg-idris/docs/docs/Postgres.Data.PostgresType.html","package":"pg-idris","namespace":"Postgres.Data.PostgresType","name":".types","typ":"TypeDictionary -> List (Oid, PType)","prefix":"","html_id":"Postgres.Data.PostgresType.(.types)"},{"html_filename":"pg-idris/docs/docs/Postgres.Data.PostgresType.html","package":"pg-idris","namespace":"Postgres.Data.PostgresType","name":"types","typ":"TypeDictionary -> List (Oid, PType)","prefix":"","html_id":"Postgres.Data.PostgresType.types"},{"html_filename":"pg-idris/docs/docs/Postgres.Data.PostgresType.html","package":"pg-idris","namespace":"Postgres.Data.PostgresType","name":"empty","typ":"TypeDictionary","prefix":"","html_id":"Postgres.Data.PostgresType.empty"},{"html_filename":"pg-idris/docs/docs/Postgres.Data.PostgresType.html","package":"pg-idris","namespace":"Postgres.Data.PostgresType","name":"typeDictionary","typ":"List (Oid, PType) -> TypeDictionary","prefix":"","html_id":"Postgres.Data.PostgresType.typeDictionary"},{"html_filename":"pg-idris/docs/docs/Postgres.Data.PostgresType.html","package":"pg-idris","namespace":"Postgres.Data.PostgresType","name":"lookup","typ":"Oid -> TypeDictionary -> PType","prefix":"","html_id":"Postgres.Data.PostgresType.lookup"},{"html_filename":"pg-idris/docs/docs/Postgres.DB.Wait.html","package":"pg-idris","namespace":"Postgres.DB.Wait","name":"pgWait","typ":"Conn -> IO Bool","prefix":"","html_id":"Postgres.DB.Wait.pgWait"},{"html_filename":"pg-idris/docs/docs/Postgres.Data.ConnectionStatus.html","package":"pg-idris","namespace":"Postgres.Data.ConnectionStatus","name":"ConnectionStatus","typ":"Type","prefix":"data","html_id":"Postgres.Data.ConnectionStatus.ConnectionStatus"},{"html_filename":"pg-idris/docs/docs/Postgres.Data.ConnectionStatus.html","package":"pg-idris","namespace":"Postgres.Data.ConnectionStatus","name":"OK","typ":"ConnectionStatus","prefix":"","html_id":"Postgres.Data.ConnectionStatus.OK"},{"html_filename":"pg-idris/docs/docs/Postgres.Data.ConnectionStatus.html","package":"pg-idris","namespace":"Postgres.Data.ConnectionStatus","name":"BAD","typ":"ConnectionStatus","prefix":"","html_id":"Postgres.Data.ConnectionStatus.BAD"},{"html_filename":"pg-idris/docs/docs/Postgres.Data.ConnectionStatus.html","package":"pg-idris","namespace":"Postgres.Data.ConnectionStatus","name":"STARTED","typ":"ConnectionStatus","prefix":"","html_id":"Postgres.Data.ConnectionStatus.STARTED"},{"html_filename":"pg-idris/docs/docs/Postgres.Data.ConnectionStatus.html","package":"pg-idris","namespace":"Postgres.Data.ConnectionStatus","name":"MADE","typ":"ConnectionStatus","prefix":"","html_id":"Postgres.Data.ConnectionStatus.MADE"},{"html_filename":"pg-idris/docs/docs/Postgres.Data.ConnectionStatus.html","package":"pg-idris","namespace":"Postgres.Data.ConnectionStatus","name":"AWAITING_RESPONSE","typ":"ConnectionStatus","prefix":"","html_id":"Postgres.Data.ConnectionStatus.AWAITING_RESPONSE"},{"html_filename":"pg-idris/docs/docs/Postgres.Data.ConnectionStatus.html","package":"pg-idris","namespace":"Postgres.Data.ConnectionStatus","name":"AUTH_OK","typ":"ConnectionStatus","prefix":"","html_id":"Postgres.Data.ConnectionStatus.AUTH_OK"},{"html_filename":"pg-idris/docs/docs/Postgres.Data.ConnectionStatus.html","package":"pg-idris","namespace":"Postgres.Data.ConnectionStatus","name":"SETENV","typ":"ConnectionStatus","prefix":"","html_id":"Postgres.Data.ConnectionStatus.SETENV"},{"html_filename":"pg-idris/docs/docs/Postgres.Data.ConnectionStatus.html","package":"pg-idris","namespace":"Postgres.Data.ConnectionStatus","name":"SSL_STARTUP","typ":"ConnectionStatus","prefix":"","html_id":"Postgres.Data.ConnectionStatus.SSL_STARTUP"},{"html_filename":"pg-idris/docs/docs/Postgres.Data.ConnectionStatus.html","package":"pg-idris","namespace":"Postgres.Data.ConnectionStatus","name":"NEEDED","typ":"ConnectionStatus","prefix":"","html_id":"Postgres.Data.ConnectionStatus.NEEDED"},{"html_filename":"pg-idris/docs/docs/Postgres.Data.ConnectionStatus.html","package":"pg-idris","namespace":"Postgres.Data.ConnectionStatus","name":"OTHER","typ":"Int -> ConnectionStatus","prefix":"","html_id":"Postgres.Data.ConnectionStatus.OTHER"},{"html_filename":"pg-idris/docs/docs/Postgres.DB.Core.html","package":"pg-idris","namespace":"Postgres.DB.Core","name":"pgOpen","typ":"HasIO io => String -> io Conn","prefix":"","html_id":"Postgres.DB.Core.pgOpen"},{"html_filename":"pg-idris/docs/docs/Postgres.DB.Core.html","package":"pg-idris","namespace":"Postgres.DB.Core","name":"pgClose","typ":"HasIO io => Conn -> io ()","prefix":"","html_id":"Postgres.DB.Core.pgClose"},{"html_filename":"pg-idris/docs/docs/Postgres.DB.Core.html","package":"pg-idris","namespace":"Postgres.DB.Core","name":"pgStatus","typ":"Conn -> ConnectionStatus","prefix":"","html_id":"Postgres.DB.Core.pgStatus"},{"html_filename":"pg-idris/docs/docs/Postgres.DB.Core.html","package":"pg-idris","namespace":"Postgres.DB.Core","name":"pgErrorMessage","typ":"HasIO io => Conn -> io String","prefix":"","html_id":"Postgres.DB.Core.pgErrorMessage"},{"html_filename":"pg-idris/docs/docs/Postgres.DB.Core.html","package":"pg-idris","namespace":"Postgres.DB.Core","name":"pgConsumeInput","typ":"Conn -> IO Bool","prefix":"","html_id":"Postgres.DB.Core.pgConsumeInput"},{"html_filename":"pg-idris/docs/docs/Postgres.Data.ResultStatus.html","package":"pg-idris","namespace":"Postgres.Data.ResultStatus","name":"ResultStatus","typ":"Type","prefix":"data","html_id":"Postgres.Data.ResultStatus.ResultStatus"},{"html_filename":"pg-idris/docs/docs/Postgres.Data.ResultStatus.html","package":"pg-idris","namespace":"Postgres.Data.ResultStatus","name":"EMPTY_QUERY","typ":"ResultStatus","prefix":"","html_id":"Postgres.Data.ResultStatus.EMPTY_QUERY"},{"html_filename":"pg-idris/docs/docs/Postgres.Data.ResultStatus.html","package":"pg-idris","namespace":"Postgres.Data.ResultStatus","name":"COMMAND_OK","typ":"ResultStatus","prefix":"","html_id":"Postgres.Data.ResultStatus.COMMAND_OK"},{"html_filename":"pg-idris/docs/docs/Postgres.Data.ResultStatus.html","package":"pg-idris","namespace":"Postgres.Data.ResultStatus","name":"TUPLES_OK","typ":"ResultStatus","prefix":"","html_id":"Postgres.Data.ResultStatus.TUPLES_OK"},{"html_filename":"pg-idris/docs/docs/Postgres.Data.ResultStatus.html","package":"pg-idris","namespace":"Postgres.Data.ResultStatus","name":"COPY_OUT","typ":"ResultStatus","prefix":"","html_id":"Postgres.Data.ResultStatus.COPY_OUT"},{"html_filename":"pg-idris/docs/docs/Postgres.Data.ResultStatus.html","package":"pg-idris","namespace":"Postgres.Data.ResultStatus","name":"COPY_IN","typ":"ResultStatus","prefix":"","html_id":"Postgres.Data.ResultStatus.COPY_IN"},{"html_filename":"pg-idris/docs/docs/Postgres.Data.ResultStatus.html","package":"pg-idris","namespace":"Postgres.Data.ResultStatus","name":"BAD_RESPONSE","typ":"ResultStatus","prefix":"","html_id":"Postgres.Data.ResultStatus.BAD_RESPONSE"},{"html_filename":"pg-idris/docs/docs/Postgres.Data.ResultStatus.html","package":"pg-idris","namespace":"Postgres.Data.ResultStatus","name":"NONFATAL_ERROR","typ":"ResultStatus","prefix":"","html_id":"Postgres.Data.ResultStatus.NONFATAL_ERROR"},{"html_filename":"pg-idris/docs/docs/Postgres.Data.ResultStatus.html","package":"pg-idris","namespace":"Postgres.Data.ResultStatus","name":"FATAL_ERROR","typ":"ResultStatus","prefix":"","html_id":"Postgres.Data.ResultStatus.FATAL_ERROR"},{"html_filename":"pg-idris/docs/docs/Postgres.Data.ResultStatus.html","package":"pg-idris","namespace":"Postgres.Data.ResultStatus","name":"COPY_BOTH","typ":"ResultStatus","prefix":"","html_id":"Postgres.Data.ResultStatus.COPY_BOTH"},{"html_filename":"pg-idris/docs/docs/Postgres.Data.ResultStatus.html","package":"pg-idris","namespace":"Postgres.Data.ResultStatus","name":"SINGLE_TUPLE","typ":"ResultStatus","prefix":"","html_id":"Postgres.Data.ResultStatus.SINGLE_TUPLE"},{"html_filename":"pg-idris/docs/docs/Postgres.Data.ResultStatus.html","package":"pg-idris","namespace":"Postgres.Data.ResultStatus","name":"OTHER","typ":"Int -> ResultStatus","prefix":"","html_id":"Postgres.Data.ResultStatus.OTHER"},{"html_filename":"pg-idris/docs/docs/Postgres.Data.Conn.html","package":"pg-idris","namespace":"Postgres.Data.Conn","name":"PGconn","typ":"Type","prefix":"data","html_id":"Postgres.Data.Conn.PGconn"},{"html_filename":"pg-idris/docs/docs/Postgres.Data.Conn.html","package":"pg-idris","namespace":"Postgres.Data.Conn","name":"Conn","typ":"Type","prefix":"data","html_id":"Postgres.Data.Conn.Conn"},{"html_filename":"pg-idris/docs/docs/Postgres.Data.Conn.html","package":"pg-idris","namespace":"Postgres.Data.Conn","name":"MkConn","typ":"Ptr PGconn -> Conn","prefix":"","html_id":"Postgres.Data.Conn.MkConn"},{"html_filename":"pg-idris/docs/docs/Postgres.Query.html","package":"pg-idris","namespace":"Postgres.Query","name":"pgStringResultsQuery","typ":"TypeDictionary => (header : Bool) -> String -> Conn -> IO (Either String (StringResultset header))","prefix":"","html_id":"Postgres.Query.pgStringResultsQuery"},{"html_filename":"pg-idris/docs/docs/Postgres.Query.html","package":"pg-idris","namespace":"Postgres.Query","name":"pgJSONResultQuery","typ":"String -> Conn -> IO (Maybe JSON)","prefix":"","html_id":"Postgres.Query.pgJSONResultQuery"},{"html_filename":"pg-idris/docs/docs/Postgres.Query.html","package":"pg-idris","namespace":"Postgres.Query","name":"pgResultQuery","typ":"TypeDictionary => (expected : Vect colCount Type) -> String -> Conn -> All Castable expected => IO (Either String (rowCount : Nat ** Vect rowCount (HVect expected)))","prefix":"","html_id":"Postgres.Query.pgResultQuery"},{"html_filename":"pg-idris/docs/docs/Postgres.Result.html","package":"pg-idris","namespace":"Postgres.Result","name":"PGresult","typ":"Type","prefix":"data","html_id":"Postgres.Result.PGresult"},{"html_filename":"pg-idris/docs/docs/Postgres.Result.html","package":"pg-idris","namespace":"Postgres.Result","name":"Result","typ":"Type","prefix":"data","html_id":"Postgres.Result.Result"},{"html_filename":"pg-idris/docs/docs/Postgres.Result.html","package":"pg-idris","namespace":"Postgres.Result","name":"MkResult","typ":"Ptr PGresult -> Result","prefix":"","html_id":"Postgres.Result.MkResult"},{"html_filename":"pg-idris/docs/docs/Postgres.Result.html","package":"pg-idris","namespace":"Postgres.Result","name":"ResultProducer","typ":"Type -> Type -> Type","prefix":"interface","html_id":"Postgres.Result.ResultProducer"},{"html_filename":"pg-idris/docs/docs/Postgres.Result.html","package":"pg-idris","namespace":"Postgres.Result","name":"exec","typ":"source -> input -> IO (Ptr PGresult)","prefix":"","html_id":"Postgres.Result.exec"},{"html_filename":"pg-idris/docs/docs/Postgres.Result.html","package":"pg-idris","namespace":"Postgres.Result","name":"withResult","typ":"ResultProducer source a => source -> a -> (Result -> IO b) -> IO b","prefix":"","html_id":"Postgres.Result.withResult"},{"html_filename":"pg-idris/docs/docs/Postgres.Result.html","package":"pg-idris","namespace":"Postgres.Result","name":"pgResultStatus","typ":"Result -> ResultStatus","prefix":"","html_id":"Postgres.Result.pgResultStatus"},{"html_filename":"pg-idris/docs/docs/Postgres.Result.html","package":"pg-idris","namespace":"Postgres.Result","name":"pgResultSuccess","typ":"Result -> Bool","prefix":"","html_id":"Postgres.Result.pgResultSuccess"},{"html_filename":"pg-idris/docs/docs/Postgres.Result.html","package":"pg-idris","namespace":"Postgres.Result","name":"pgResultErrorMessage","typ":"Result -> Maybe String","prefix":"","html_id":"Postgres.Result.pgResultErrorMessage"},{"html_filename":"pg-idris/docs/docs/Postgres.Result.html","package":"pg-idris","namespace":"Postgres.Result","name":"TupleResult","typ":"Nat -> Nat -> Type","prefix":"data","html_id":"Postgres.Result.TupleResult"},{"html_filename":"pg-idris/docs/docs/Postgres.Result.html","package":"pg-idris","namespace":"Postgres.Result","name":"MkTupleResult","typ":"(res : Result) -> TupleResult (resultRowCount res) (resultColCount res)","prefix":"","html_id":"Postgres.Result.MkTupleResult"},{"html_filename":"pg-idris/docs/docs/Postgres.Result.html","package":"pg-idris","namespace":"Postgres.Result","name":"tupleResult","typ":"(res : Result) -> Maybe (TupleResult (resultRowCount res) (resultColCount res))","prefix":"","html_id":"Postgres.Result.tupleResult"},{"html_filename":"pg-idris/docs/docs/Postgres.Result.html","package":"pg-idris","namespace":"Postgres.Result","name":"pgResultSize","typ":"TupleResult r c -> (Nat, Nat)","prefix":"","html_id":"Postgres.Result.pgResultSize"},{"html_filename":"pg-idris/docs/docs/Postgres.Result.html","package":"pg-idris","namespace":"Postgres.Result","name":"pgResultStringValue","typ":"TupleResult rows cols -> Fin rows -> Fin cols -> String","prefix":"","html_id":"Postgres.Result.pgResultStringValue"},{"html_filename":"pg-idris/docs/docs/Postgres.Result.html","package":"pg-idris","namespace":"Postgres.Result","name":"pgResultNullableStringValue","typ":"TupleResult rows cols -> Fin rows -> Fin cols -> Maybe String","prefix":"","html_id":"Postgres.Result.pgResultNullableStringValue"},{"html_filename":"pg-idris/docs/docs/Postgres.Result.html","package":"pg-idris","namespace":"Postgres.Result","name":"ColHeader","typ":"Type","prefix":"record","html_id":"Postgres.Result.ColHeader"},{"html_filename":"pg-idris/docs/docs/Postgres.Result.html","package":"pg-idris","namespace":"Postgres.Result","name":"MkHeader","typ":"String -> PType -> ColHeader","prefix":"","html_id":"Postgres.Result.MkHeader"},{"html_filename":"pg-idris/docs/docs/Postgres.Result.html","package":"pg-idris","namespace":"Postgres.Result","name":".name","typ":"ColHeader -> String","prefix":"","html_id":"Postgres.Result.ColHeader.(.name)"},{"html_filename":"pg-idris/docs/docs/Postgres.Result.html","package":"pg-idris","namespace":"Postgres.Result","name":".type","typ":"ColHeader -> PType","prefix":"","html_id":"Postgres.Result.ColHeader.(.type)"},{"html_filename":"pg-idris/docs/docs/Postgres.Result.html","package":"pg-idris","namespace":"Postgres.Result","name":"name","typ":"ColHeader -> String","prefix":"","html_id":"Postgres.Result.ColHeader.name"},{"html_filename":"pg-idris/docs/docs/Postgres.Result.html","package":"pg-idris","namespace":"Postgres.Result","name":"type","typ":"ColHeader -> PType","prefix":"","html_id":"Postgres.Result.ColHeader.type"},{"html_filename":"pg-idris/docs/docs/Postgres.Result.html","package":"pg-idris","namespace":"Postgres.Result","name":"pgStringResultset","typ":"TupleResult rows cols -> Vect rows (Vect cols (Lazy String))","prefix":"","html_id":"Postgres.Result.pgStringResultset"},{"html_filename":"pg-idris/docs/docs/Postgres.Result.html","package":"pg-idris","namespace":"Postgres.Result","name":"StringResultset","typ":"Bool -> Type","prefix":"","html_id":"Postgres.Result.StringResultset"},{"html_filename":"pg-idris/docs/docs/Postgres.Result.html","package":"pg-idris","namespace":"Postgres.Result","name":"pgNullableStringResultset","typ":"TupleResult rows cols -> Vect rows (Vect cols (Lazy (Maybe String)))","prefix":"","html_id":"Postgres.Result.pgNullableStringResultset"},{"html_filename":"pg-idris/docs/docs/Postgres.Result.html","package":"pg-idris","namespace":"Postgres.Result","name":"pgResultsetColNames","typ":"TupleResult rows cols -> Vect cols String","prefix":"","html_id":"Postgres.Result.pgResultsetColNames"},{"html_filename":"pg-idris/docs/docs/Postgres.Result.html","package":"pg-idris","namespace":"Postgres.Result","name":"pgResultsetColTypes","typ":"TypeDictionary => TupleResult rows cols -> Vect cols PType","prefix":"","html_id":"Postgres.Result.pgResultsetColTypes"},{"html_filename":"pg-idris/docs/docs/Postgres.Data.PostgresValue.html","package":"pg-idris","namespace":"Postgres.Data.PostgresValue","name":"PValue","typ":"PType -> Type","prefix":"data","html_id":"Postgres.Data.PostgresValue.PValue"},{"html_filename":"pg-idris/docs/docs/Postgres.Data.PostgresValue.html","package":"pg-idris","namespace":"Postgres.Data.PostgresValue","name":"Raw","typ":"String -> PValue p","prefix":"","html_id":"Postgres.Data.PostgresValue.Raw"},{"html_filename":"pg-idris/docs/docs/Postgres.Data.PostgresValue.html","package":"pg-idris","namespace":"Postgres.Data.PostgresValue","name":"rawString","typ":"PValue t -> String","prefix":"","html_id":"Postgres.Data.PostgresValue.rawString"},{"html_filename":"pg-idris/docs/docs/Postgres.Data.PostgresValue.html","package":"pg-idris","namespace":"Postgres.Data.PostgresValue","name":"IdrCast","typ":"PType -> Type -> Type","prefix":"interface","html_id":"Postgres.Data.PostgresValue.IdrCast"},{"html_filename":"pg-idris/docs/docs/Postgres.Data.PostgresValue.html","package":"pg-idris","namespace":"Postgres.Data.PostgresValue","name":"toIdris","typ":"PValue pt -> Maybe ty","prefix":"","html_id":"Postgres.Data.PostgresValue.toIdris"},{"html_filename":"pg-idris/docs/docs/Postgres.Data.PostgresValue.html","package":"pg-idris","namespace":"Postgres.Data.PostgresValue","name":"PGCast","typ":"PType -> Type -> Type","prefix":"interface","html_id":"Postgres.Data.PostgresValue.PGCast"},{"html_filename":"pg-idris/docs/docs/Postgres.Data.PostgresValue.html","package":"pg-idris","namespace":"Postgres.Data.PostgresValue","name":"toPostgres","typ":"ty -> PValue pt","prefix":"","html_id":"Postgres.Data.PostgresValue.toPostgres"},{"html_filename":"pg-idris/docs/docs/Postgres.Data.PostgresValue.html","package":"pg-idris","namespace":"Postgres.Data.PostgresValue","name":"DBStringCast","typ":"Type -> Type","prefix":"interface","html_id":"Postgres.Data.PostgresValue.DBStringCast"},{"html_filename":"pg-idris/docs/docs/Postgres.Data.PostgresValue.html","package":"pg-idris","namespace":"Postgres.Data.PostgresValue","name":"dbCast","typ":"String -> Either String a","prefix":"","html_id":"Postgres.Data.PostgresValue.dbCast"},{"html_filename":"pg-idris/docs/docs/Postgres.Data.PostgresValue.html","package":"pg-idris","namespace":"Postgres.Data.PostgresValue","name":"Castable","typ":"Type -> Type","prefix":"data","html_id":"Postgres.Data.PostgresValue.Castable"},{"html_filename":"pg-idris/docs/docs/Postgres.Data.PostgresValue.html","package":"pg-idris","namespace":"Postgres.Data.PostgresValue","name":"Cast","typ":"DBStringCast ty => Castable ty","prefix":"","html_id":"Postgres.Data.PostgresValue.Cast"},{"html_filename":"pg-idris/docs/docs/Postgres.Data.PostgresValue.html","package":"pg-idris","namespace":"Postgres.Data.PostgresValue","name":"CastMaybe","typ":"DBStringCast ty => Castable (Maybe ty)","prefix":"","html_id":"Postgres.Data.PostgresValue.CastMaybe"},{"html_filename":"pg-idris/docs/docs/Postgres.Data.PostgresValue.html","package":"pg-idris","namespace":"Postgres.Data.PostgresValue","name":"asDefaultType","typ":"Castable t -> Maybe String -> Either String t","prefix":"","html_id":"Postgres.Data.PostgresValue.asDefaultType"},{"html_filename":"pg-idris/docs/docs/Postgres.Data.PostgresTable.html","package":"pg-idris","namespace":"Postgres.Data.PostgresTable","name":"Ident","typ":"Type","prefix":"data","html_id":"Postgres.Data.PostgresTable.Ident"},{"html_filename":"pg-idris/docs/docs/Postgres.Data.PostgresTable.html","package":"pg-idris","namespace":"Postgres.Data.PostgresTable","name":"Id","typ":"String -> Ident","prefix":"","html_id":"Postgres.Data.PostgresTable.Id"},{"html_filename":"pg-idris/docs/docs/Postgres.Data.PostgresTable.html","package":"pg-idris","namespace":"Postgres.Data.PostgresTable","name":"Alias","typ":"Type","prefix":"data","html_id":"Postgres.Data.PostgresTable.Alias"},{"html_filename":"pg-idris/docs/docs/Postgres.Data.PostgresTable.html","package":"pg-idris","namespace":"Postgres.Data.PostgresTable","name":"Named","typ":"String -> Alias","prefix":"","html_id":"Postgres.Data.PostgresTable.Named"},{"html_filename":"pg-idris/docs/docs/Postgres.Data.PostgresTable.html","package":"pg-idris","namespace":"Postgres.Data.PostgresTable","name":"Generated","typ":"Nat -> Alias","prefix":"","html_id":"Postgres.Data.PostgresTable.Generated"},{"html_filename":"pg-idris/docs/docs/Postgres.Data.PostgresTable.html","package":"pg-idris","namespace":"Postgres.Data.PostgresTable","name":"aliasIdentifier","typ":"Alias -> Ident","prefix":"","html_id":"Postgres.Data.PostgresTable.aliasIdentifier"},{"html_filename":"pg-idris/docs/docs/Postgres.Data.PostgresTable.html","package":"pg-idris","namespace":"Postgres.Data.PostgresTable","name":"toAlias","typ":"Ident -> Alias","prefix":"","html_id":"Postgres.Data.PostgresTable.toAlias"},{"html_filename":"pg-idris/docs/docs/Postgres.Data.PostgresTable.html","package":"pg-idris","namespace":"Postgres.Data.PostgresTable","name":"TableStatement","typ":"Type","prefix":"data","html_id":"Postgres.Data.PostgresTable.TableStatement"},{"html_filename":"pg-idris/docs/docs/Postgres.Data.PostgresTable.html","package":"pg-idris","namespace":"Postgres.Data.PostgresTable","name":"Identifier","typ":"String -> Maybe Alias -> TableStatement","prefix":"","html_id":"Postgres.Data.PostgresTable.Identifier"},{"html_filename":"pg-idris/docs/docs/Postgres.Data.PostgresTable.html","package":"pg-idris","namespace":"Postgres.Data.PostgresTable","name":"Subquery","typ":"String -> Alias -> TableStatement","prefix":"","html_id":"Postgres.Data.PostgresTable.Subquery"},{"html_filename":"pg-idris/docs/docs/Postgres.Data.PostgresTable.html","package":"pg-idris","namespace":"Postgres.Data.PostgresTable","name":"Fragment","typ":"String -> TableStatement","prefix":"","html_id":"Postgres.Data.PostgresTable.Fragment"},{"html_filename":"pg-idris/docs/docs/Postgres.Data.PostgresTable.html","package":"pg-idris","namespace":"Postgres.Data.PostgresTable","name":"tableAlias","typ":"TableStatement -> Maybe Alias","prefix":"","html_id":"Postgres.Data.PostgresTable.tableAlias"},{"html_filename":"pg-idris/docs/docs/Postgres.Data.PostgresTable.html","package":"pg-idris","namespace":"Postgres.Data.PostgresTable","name":"tableAliasOrName","typ":"TableStatement -> Maybe Ident","prefix":"","html_id":"Postgres.Data.PostgresTable.tableAliasOrName"},{"html_filename":"pg-idris/docs/docs/Postgres.Data.PostgresTable.html","package":"pg-idris","namespace":"Postgres.Data.PostgresTable","name":"named","typ":"String -> {default Nothing _ : Maybe Alias} -> TableStatement","prefix":"","html_id":"Postgres.Data.PostgresTable.named"},{"html_filename":"pg-idris/docs/docs/Postgres.Data.PostgresTable.html","package":"pg-idris","namespace":"Postgres.Data.PostgresTable","name":"subquery","typ":"String -> Alias -> TableStatement","prefix":"","html_id":"Postgres.Data.PostgresTable.subquery"},{"html_filename":"pg-idris/docs/docs/Postgres.Data.PostgresTable.html","package":"pg-idris","namespace":"Postgres.Data.PostgresTable","name":"ColumnIdentifier","typ":"Type","prefix":"record","html_id":"Postgres.Data.PostgresTable.ColumnIdentifier"},{"html_filename":"pg-idris/docs/docs/Postgres.Data.PostgresTable.html","package":"pg-idris","namespace":"Postgres.Data.PostgresTable","name":"MkColumnId","typ":"Maybe Alias -> String -> ColumnIdentifier","prefix":"","html_id":"Postgres.Data.PostgresTable.MkColumnId"},{"html_filename":"pg-idris/docs/docs/Postgres.Data.PostgresTable.html","package":"pg-idris","namespace":"Postgres.Data.PostgresTable","name":".name","typ":"ColumnIdentifier -> String","prefix":"","html_id":"Postgres.Data.PostgresTable.ColumnIdentifier.(.name)"},{"html_filename":"pg-idris/docs/docs/Postgres.Data.PostgresTable.html","package":"pg-idris","namespace":"Postgres.Data.PostgresTable","name":".sourceTable","typ":"ColumnIdentifier -> Maybe Alias","prefix":"","html_id":"Postgres.Data.PostgresTable.ColumnIdentifier.(.sourceTable)"},{"html_filename":"pg-idris/docs/docs/Postgres.Data.PostgresTable.html","package":"pg-idris","namespace":"Postgres.Data.PostgresTable","name":"sourceTable","typ":"ColumnIdentifier -> Maybe Alias","prefix":"","html_id":"Postgres.Data.PostgresTable.ColumnIdentifier.sourceTable"},{"html_filename":"pg-idris/docs/docs/Postgres.Data.PostgresTable.html","package":"pg-idris","namespace":"Postgres.Data.PostgresTable","name":"name","typ":"ColumnIdentifier -> String","prefix":"","html_id":"Postgres.Data.PostgresTable.ColumnIdentifier.name"},{"html_filename":"pg-idris/docs/docs/Postgres.Data.PostgresTable.html","package":"pg-idris","namespace":"Postgres.Data.PostgresTable","name":"replaceSource","typ":"Maybe Alias -> ColumnIdentifier -> ColumnIdentifier","prefix":"","html_id":"Postgres.Data.PostgresTable.replaceSource"},{"html_filename":"pg-idris/docs/docs/Postgres.Data.PostgresTable.html","package":"pg-idris","namespace":"Postgres.Data.PostgresTable","name":"forgetSource","typ":"ColumnIdentifier -> ColumnIdentifier","prefix":"","html_id":"Postgres.Data.PostgresTable.forgetSource"},{"html_filename":"pg-idris/docs/docs/Postgres.Data.PostgresTable.html","package":"pg-idris","namespace":"Postgres.Data.PostgresTable","name":"AnonymousColumnIdentifier","typ":"ColumnIdentifier -> Type","prefix":"data","html_id":"Postgres.Data.PostgresTable.AnonymousColumnIdentifier"},{"html_filename":"pg-idris/docs/docs/Postgres.Data.PostgresTable.html","package":"pg-idris","namespace":"Postgres.Data.PostgresTable","name":"Anon","typ":"AnonymousColumnIdentifier (MkColumnId Nothing {_:9845})","prefix":"","html_id":"Postgres.Data.PostgresTable.Anon"},{"html_filename":"pg-idris/docs/docs/Postgres.Data.PostgresTable.html","package":"pg-idris","namespace":"Postgres.Data.PostgresTable","name":"PostgresTable","typ":"Type -> Type","prefix":"interface","html_id":"Postgres.Data.PostgresTable.PostgresTable"},{"html_filename":"pg-idris/docs/docs/Postgres.Data.PostgresTable.html","package":"pg-idris","namespace":"Postgres.Data.PostgresTable","name":"tableStatement","typ":"t -> TableStatement","prefix":"","html_id":"Postgres.Data.PostgresTable.tableStatement"},{"html_filename":"pg-idris/docs/docs/Postgres.Data.PostgresTable.html","package":"pg-idris","namespace":"Postgres.Data.PostgresTable","name":"columns","typ":"t -> List (ColumnIdentifier, Exists PColType)","prefix":"","html_id":"Postgres.Data.PostgresTable.columns"},{"html_filename":"pg-idris/docs/docs/Postgres.Data.PostgresTable.html","package":"pg-idris","namespace":"Postgres.Data.PostgresTable","name":"as","typ":"t -> String -> t","prefix":"","html_id":"Postgres.Data.PostgresTable.as"},{"html_filename":"pg-idris/docs/docs/Postgres.Data.PostgresTable.html","package":"pg-idris","namespace":"Postgres.Data.PostgresTable","name":"alias","typ":"PostgresTable t => t -> Maybe Alias","prefix":"","html_id":"Postgres.Data.PostgresTable.alias"},{"html_filename":"pg-idris/docs/docs/Postgres.Data.PostgresTable.html","package":"pg-idris","namespace":"Postgres.Data.PostgresTable","name":"aliasOrName","typ":"PostgresTable t => t -> Maybe Alias","prefix":"","html_id":"Postgres.Data.PostgresTable.aliasOrName"},{"html_filename":"pg-idris/docs/docs/Postgres.Data.PostgresTable.html","package":"pg-idris","namespace":"Postgres.Data.PostgresTable","name":"RuntimeTable","typ":"Type","prefix":"record","html_id":"Postgres.Data.PostgresTable.RuntimeTable"},{"html_filename":"pg-idris/docs/docs/Postgres.Data.PostgresTable.html","package":"pg-idris","namespace":"Postgres.Data.PostgresTable","name":"RT","typ":"TableStatement -> List (ColumnIdentifier, Exists PColType) -> RuntimeTable","prefix":"","html_id":"Postgres.Data.PostgresTable.RT"},{"html_filename":"pg-idris/docs/docs/Postgres.Data.PostgresTable.html","package":"pg-idris","namespace":"Postgres.Data.PostgresTable","name":".columns","typ":"RuntimeTable -> List (ColumnIdentifier, Exists PColType)","prefix":"","html_id":"Postgres.Data.PostgresTable.RuntimeTable.(.columns)"},{"html_filename":"pg-idris/docs/docs/Postgres.Data.PostgresTable.html","package":"pg-idris","namespace":"Postgres.Data.PostgresTable","name":".tableStatement","typ":"RuntimeTable -> TableStatement","prefix":"","html_id":"Postgres.Data.PostgresTable.RuntimeTable.(.tableStatement)"},{"html_filename":"pg-idris/docs/docs/Postgres.Data.PostgresTable.html","package":"pg-idris","namespace":"Postgres.Data.PostgresTable","name":"PersistedTable","typ":"Type","prefix":"record","html_id":"Postgres.Data.PostgresTable.PersistedTable"},{"html_filename":"pg-idris/docs/docs/Postgres.Data.PostgresTable.html","package":"pg-idris","namespace":"Postgres.Data.PostgresTable","name":"PT","typ":"String -> {default Nothing _ : Maybe Alias} -> List (String, Exists PColType) -> PersistedTable","prefix":"","html_id":"Postgres.Data.PostgresTable.PT"},{"html_filename":"pg-idris/docs/docs/Postgres.Data.PostgresTable.html","package":"pg-idris","namespace":"Postgres.Data.PostgresTable","name":".alias","typ":"PersistedTable -> Maybe Alias","prefix":"","html_id":"Postgres.Data.PostgresTable.PersistedTable.(.alias)"},{"html_filename":"pg-idris/docs/docs/Postgres.Data.PostgresTable.html","package":"pg-idris","namespace":"Postgres.Data.PostgresTable","name":".tableName","typ":"PersistedTable -> String","prefix":"","html_id":"Postgres.Data.PostgresTable.PersistedTable.(.tableName)"},{"html_filename":"pg-idris/docs/docs/Postgres.Data.PostgresTable.html","package":"pg-idris","namespace":"Postgres.Data.PostgresTable","name":"tableName","typ":"PersistedTable -> String","prefix":"","html_id":"Postgres.Data.PostgresTable.PersistedTable.tableName"},{"html_filename":"pg-idris/docs/docs/Postgres.Data.PostgresTable.html","package":"pg-idris","namespace":"Postgres.Data.PostgresTable","name":"col","typ":"Nullability -> PType -> Exists PColType","prefix":"","html_id":"Postgres.Data.PostgresTable.col"},{"html_filename":"pg-idris/docs/docs/Postgres.Data.PostgresTable.html","package":"pg-idris","namespace":"Postgres.Data.PostgresTable","name":"pgTable","typ":"String -> List (String, (Nullability, PType)) -> PersistedTable","prefix":"","html_id":"Postgres.Data.PostgresTable.pgTable"},{"html_filename":"pg-idris/docs/docs/Postgres.Data.PostgresTable.html","package":"pg-idris","namespace":"Postgres.Data.PostgresTable","name":"LooseColumnMapping","typ":"(0 _ : (PType -> Type -> Type)) -> List (ColumnIdentifier, Exists PColType) -> (ColumnIdentifier, Type) -> Type","prefix":"data","html_id":"Postgres.Data.PostgresTable.LooseColumnMapping"},{"html_filename":"pg-idris/docs/docs/Postgres.Data.PostgresTable.html","package":"pg-idris","namespace":"Postgres.Data.PostgresTable","name":"HereNul","typ":"(ident : ColumnIdentifier) -> (ty : Type) -> castTy pt ty => LooseColumnMapping castTy ((ident, Evidence pt (MkColType Nullable pt)) :: xs) (ident, Maybe ty)","prefix":"","html_id":"Postgres.Data.PostgresTable.HereNul"},{"html_filename":"pg-idris/docs/docs/Postgres.Data.PostgresTable.html","package":"pg-idris","namespace":"Postgres.Data.PostgresTable","name":"HereNulLoose","typ":"(columnName : String) -> (ty : Type) -> castTy pt ty => LooseColumnMapping castTy ((MkColumnId {_:10556} columnName, Evidence pt (MkColType Nullable pt)) :: xs) (MkColumnId Nothing columnName, Maybe ty)","prefix":"","html_id":"Postgres.Data.PostgresTable.HereNulLoose"},{"html_filename":"pg-idris/docs/docs/Postgres.Data.PostgresTable.html","package":"pg-idris","namespace":"Postgres.Data.PostgresTable","name":"Here","typ":"(ident : ColumnIdentifier) -> (ty : Type) -> castTy pt ty => LooseColumnMapping castTy ((ident, Evidence pt (MkColType NonNullable pt)) :: xs) (ident, ty)","prefix":"","html_id":"Postgres.Data.PostgresTable.Here"},{"html_filename":"pg-idris/docs/docs/Postgres.Data.PostgresTable.html","package":"pg-idris","namespace":"Postgres.Data.PostgresTable","name":"HereLoose","typ":"(columnName : String) -> (ty : Type) -> castTy pt ty => LooseColumnMapping castTy ((MkColumnId {_:10643} columnName, Evidence pt (MkColType NonNullable pt)) :: xs) (MkColumnId Nothing columnName, ty)","prefix":"","html_id":"Postgres.Data.PostgresTable.HereLoose"},{"html_filename":"pg-idris/docs/docs/Postgres.Data.PostgresTable.html","package":"pg-idris","namespace":"Postgres.Data.PostgresTable","name":"There","typ":"LooseColumnMapping castTy xs (ident, ty) -> LooseColumnMapping castTy (x :: xs) (ident, ty)","prefix":"","html_id":"Postgres.Data.PostgresTable.There"},{"html_filename":"pg-idris/docs/docs/Postgres.Data.PostgresTable.html","package":"pg-idris","namespace":"Postgres.Data.PostgresTable","name":"HasLooseMappings","typ":"(0 _ : (PType -> Type -> Type)) -> PostgresTable t => t -> Vect n (ColumnIdentifier, Type) -> Type","prefix":"","html_id":"Postgres.Data.PostgresTable.HasLooseMappings"},{"html_filename":"pg-idris/docs/docs/Postgres.Data.PostgresTable.html","package":"pg-idris","namespace":"Postgres.Data.PostgresTable","name":"ColumnMapping","typ":"(0 _ : (PType -> Type -> Type)) -> List (ColumnIdentifier, Exists PColType) -> (ColumnIdentifier, Type) -> Type","prefix":"data","html_id":"Postgres.Data.PostgresTable.Strict.ColumnMapping"},{"html_filename":"pg-idris/docs/docs/Postgres.Data.PostgresTable.html","package":"pg-idris","namespace":"Postgres.Data.PostgresTable","name":"HasMappings","typ":"(0 _ : (PType -> Type -> Type)) -> PostgresTable t => t -> Vect n (ColumnIdentifier, Type) -> Type","prefix":"","html_id":"Postgres.Data.PostgresTable.Strict.HasMappings"},{"html_filename":"pg-idris/docs/docs/Postgres.Data.PostgresTable.html","package":"pg-idris","namespace":"Postgres.Data.PostgresTable","name":"select","typ":"{auto {conArg:11089} : PostgresTable t} -> (table : t) -> (cols : Vect n (ColumnIdentifier, Type)) -> {auto 0 _ : HasMappings IdrCast table cols} -> String","prefix":"","html_id":"Postgres.Data.PostgresTable.select"},{"html_filename":"pg-idris/docs/docs/Postgres.Data.PostgresTable.html","package":"pg-idris","namespace":"Postgres.Data.PostgresTable","name":"insert","typ":"(table : PersistedTable) -> (cols : Vect n ColumnIdentifier) -> HVect colTypes -> HasLooseMappings PGCast table (cols `zip` colTypes) => String","prefix":"","html_id":"Postgres.Data.PostgresTable.insert"},{"html_filename":"pg-idris/docs/docs/Postgres.Data.PostgresTable.html","package":"pg-idris","namespace":"Postgres.Data.PostgresTable","name":"Join","typ":"t1 -> t2 -> Type","prefix":"data","html_id":"Postgres.Data.PostgresTable.Join"},{"html_filename":"pg-idris/docs/docs/Postgres.Data.PostgresTable.html","package":"pg-idris","namespace":"Postgres.Data.PostgresTable","name":"On","typ":"{auto {conArg:11386} : PostgresTable t} -> {auto {conArg:11389} : PostgresTable u} -> (c1 : ColumnIdentifier) -> (c2 : ColumnIdentifier) -> {auto 0 _ : Elem c1 (fst <$> columns t1)} -> {auto 0 _ : Elem c2 (fst <$> columns t2)} -> Join t1 t2","prefix":"","html_id":"Postgres.Data.PostgresTable.On"},{"html_filename":"pg-idris/docs/docs/Postgres.Data.PostgresTable.html","package":"pg-idris","namespace":"Postgres.Data.PostgresTable","name":"HasOnMapping","typ":"ColumnIdentifier -> PostgresTable t => t -> Type","prefix":"","html_id":"Postgres.Data.PostgresTable.HasOnMapping"},{"html_filename":"pg-idris/docs/docs/Postgres.Data.PostgresTable.html","package":"pg-idris","namespace":"Postgres.Data.PostgresTable","name":"elemForOnMapping","typ":"{auto {conArg:11496} : PostgresTable t} -> (table : t) -> (c : ColumnIdentifier) -> HasOnMapping c table -> (c' : ColumnIdentifier ** Elem c' (fst <$> columns table))","prefix":"","html_id":"Postgres.Data.PostgresTable.elemForOnMapping"},{"html_filename":"pg-idris/docs/docs/Postgres.Data.PostgresTable.html","package":"pg-idris","namespace":"Postgres.Data.PostgresTable","name":"(==)","typ":"{auto {conArg:11566} : PostgresTable t} -> {auto {conArg:11569} : PostgresTable u} -> (c1 : ColumnIdentifier) -> (c2 : ColumnIdentifier) -> HasOnMapping c1 t1 => HasOnMapping c2 t2 => Join t1 t2","prefix":"","html_id":"Postgres.Data.PostgresTable.(==)"},{"html_filename":"pg-idris/docs/docs/Postgres.Data.PostgresTable.html","package":"pg-idris","namespace":"Postgres.Data.PostgresTable","name":"column1","typ":"Join t u -> ColumnIdentifier","prefix":"","html_id":"Postgres.Data.PostgresTable.Join.column1"},{"html_filename":"pg-idris/docs/docs/Postgres.Data.PostgresTable.html","package":"pg-idris","namespace":"Postgres.Data.PostgresTable","name":"column2","typ":"Join t u -> ColumnIdentifier","prefix":"","html_id":"Postgres.Data.PostgresTable.Join.column2"},{"html_filename":"pg-idris/docs/docs/Postgres.Data.PostgresTable.html","package":"pg-idris","namespace":"Postgres.Data.PostgresTable","name":"innerJoin'","typ":"PostgresTable t => (table1 : t) -> PostgresTable u => (table2 : u) -> Join table1 table2 -> RuntimeTable","prefix":"","html_id":"Postgres.Data.PostgresTable.innerJoin'"},{"html_filename":"pg-idris/docs/docs/Postgres.Data.PostgresTable.html","package":"pg-idris","namespace":"Postgres.Data.PostgresTable","name":"leftJoin'","typ":"PostgresTable t => (table1 : t) -> PostgresTable u => (table2 : u) -> Join table1 table2 -> RuntimeTable","prefix":"","html_id":"Postgres.Data.PostgresTable.leftJoin'"},{"html_filename":"pg-idris/docs/docs/Postgres.Data.PostgresTable.html","package":"pg-idris","namespace":"Postgres.Data.PostgresTable","name":"rightJoin'","typ":"PostgresTable t => (table1 : t) -> PostgresTable u => (table2 : u) -> Join table1 table2 -> RuntimeTable","prefix":"","html_id":"Postgres.Data.PostgresTable.rightJoin'"},{"html_filename":"pg-idris/docs/docs/Postgres.Data.PostgresTable.html","package":"pg-idris","namespace":"Postgres.Data.PostgresTable","name":"JoinType","typ":"Type","prefix":"data","html_id":"Postgres.Data.PostgresTable.JoinType"},{"html_filename":"pg-idris/docs/docs/Postgres.Data.PostgresTable.html","package":"pg-idris","namespace":"Postgres.Data.PostgresTable","name":"Inner","typ":"JoinType","prefix":"","html_id":"Postgres.Data.PostgresTable.Inner"},{"html_filename":"pg-idris/docs/docs/Postgres.Data.PostgresTable.html","package":"pg-idris","namespace":"Postgres.Data.PostgresTable","name":"Left","typ":"JoinType","prefix":"","html_id":"Postgres.Data.PostgresTable.Left"},{"html_filename":"pg-idris/docs/docs/Postgres.Data.PostgresTable.html","package":"pg-idris","namespace":"Postgres.Data.PostgresTable","name":"Right","typ":"JoinType","prefix":"","html_id":"Postgres.Data.PostgresTable.Right"},{"html_filename":"pg-idris/docs/docs/Postgres.Data.PostgresTable.html","package":"pg-idris","namespace":"Postgres.Data.PostgresTable","name":"TablePair","typ":"table1 -> table2 -> Type","prefix":"data","html_id":"Postgres.Data.PostgresTable.TablePair"},{"html_filename":"pg-idris/docs/docs/Postgres.Data.PostgresTable.html","package":"pg-idris","namespace":"Postgres.Data.PostgresTable","name":"MkTP","typ":"JoinType -> PostgresTable t => PostgresTable u => (table1 : t) -> (table2 : u) -> TablePair table1 table2","prefix":"","html_id":"Postgres.Data.PostgresTable.MkTP"},{"html_filename":"pg-idris/docs/docs/Postgres.Data.PostgresTable.html","package":"pg-idris","namespace":"Postgres.Data.PostgresTable","name":"innerJoin","typ":"PostgresTable t => PostgresTable u => (table1 : t) -> (table2 : u) -> TablePair table1 table2","prefix":"","html_id":"Postgres.Data.PostgresTable.innerJoin"},{"html_filename":"pg-idris/docs/docs/Postgres.Data.PostgresTable.html","package":"pg-idris","namespace":"Postgres.Data.PostgresTable","name":"leftJoin","typ":"PostgresTable t => PostgresTable u => (table1 : t) -> (table2 : u) -> TablePair table1 table2","prefix":"","html_id":"Postgres.Data.PostgresTable.leftJoin"},{"html_filename":"pg-idris/docs/docs/Postgres.Data.PostgresTable.html","package":"pg-idris","namespace":"Postgres.Data.PostgresTable","name":"rightJoin","typ":"PostgresTable t => PostgresTable u => (table1 : t) -> (table2 : u) -> TablePair table1 table2","prefix":"","html_id":"Postgres.Data.PostgresTable.rightJoin"},{"html_filename":"pg-idris/docs/docs/Postgres.Data.PostgresTable.html","package":"pg-idris","namespace":"Postgres.Data.PostgresTable","name":"onColumns","typ":"TablePair table1 table2 -> Join table1 table2 -> RuntimeTable","prefix":"","html_id":"Postgres.Data.PostgresTable.onColumns"},{"html_filename":"pg-idris/docs/docs/Postgres.Data.PostgresTable.html","package":"pg-idris","namespace":"Postgres.Data.PostgresTable","name":"allCastable","typ":"{auto {conArg:12468} : PostgresTable t} -> (table : t) -> HasMappings IdrCast table cols => All Castable (snd <$> cols)","prefix":"","html_id":"Postgres.Data.PostgresTable.allCastable"},{"html_filename":"pg-idris/docs/docs/Postgres.FFI.Utility.html","package":"pg-idris","namespace":"Postgres.FFI.Utility","name":"libpq","typ":"String -> String","prefix":"","html_id":"Postgres.FFI.Utility.libpq"},{"html_filename":"pg-idris/docs/docs/Postgres.FFI.Utility.html","package":"pg-idris","namespace":"Postgres.FFI.Utility","name":"cHelper","typ":"String -> String","prefix":"","html_id":"Postgres.FFI.Utility.cHelper"},{"html_filename":"pg-idris/docs/docs/Postgres.FFI.Utility.html","package":"pg-idris","namespace":"Postgres.FFI.Utility","name":"nLibpq","typ":"String -> String","prefix":"","html_id":"Postgres.FFI.Utility.nLibpq"},{"html_filename":"pg-idris/docs/docs/Postgres.FFI.Utility.html","package":"pg-idris","namespace":"Postgres.FFI.Utility","name":"prim__string_value","typ":"Ptr String -> String","prefix":"","html_id":"Postgres.FFI.Utility.prim__string_value"},{"html_filename":"pg-idris/docs/docs/Postgres.Notification.html","package":"pg-idris","namespace":"Postgres.Notification","name":"Notification","typ":"Type","prefix":"record","html_id":"Postgres.Notification.Notification"},{"html_filename":"pg-idris/docs/docs/Postgres.Notification.html","package":"pg-idris","namespace":"Postgres.Notification","name":"MkNotification","typ":"String -> String -> Notification","prefix":"","html_id":"Postgres.Notification.MkNotification"},{"html_filename":"pg-idris/docs/docs/Postgres.Notification.html","package":"pg-idris","namespace":"Postgres.Notification","name":".channel","typ":"Notification -> String","prefix":"","html_id":"Postgres.Notification.Notification.(.channel)"},{"html_filename":"pg-idris/docs/docs/Postgres.Notification.html","package":"pg-idris","namespace":"Postgres.Notification","name":".payload","typ":"Notification -> String","prefix":"","html_id":"Postgres.Notification.Notification.(.payload)"},{"html_filename":"pg-idris/docs/docs/Postgres.Notification.html","package":"pg-idris","namespace":"Postgres.Notification","name":"channel","typ":"Notification -> String","prefix":"","html_id":"Postgres.Notification.Notification.channel"},{"html_filename":"pg-idris/docs/docs/Postgres.Notification.html","package":"pg-idris","namespace":"Postgres.Notification","name":"payload","typ":"Notification -> String","prefix":"","html_id":"Postgres.Notification.Notification.payload"},{"html_filename":"pg-idris/docs/docs/Postgres.Notification.html","package":"pg-idris","namespace":"Postgres.Notification","name":"pgListen","typ":"String -> Conn -> IO ResultStatus","prefix":"","html_id":"Postgres.Notification.pgListen"},{"html_filename":"pg-idris/docs/docs/Postgres.Notification.html","package":"pg-idris","namespace":"Postgres.Notification","name":"pgNextNotification","typ":"Conn -> IO (Maybe Notification)","prefix":"","html_id":"Postgres.Notification.pgNextNotification"},{"html_filename":"pg-idris/docs/docs/Postgres.Notification.html","package":"pg-idris","namespace":"Postgres.Notification","name":"pgNotificationStream","typ":"Conn -> Stream (IO Notification)","prefix":"","html_id":"Postgres.Notification.pgNotificationStream"},{"html_filename":"pg-idris/docs/docs/Postgres.LoadTypes.html","package":"pg-idris","namespace":"Postgres.LoadTypes","name":"pgLoadTypes","typ":"HasIO io => Conn -> io (Either String TypeDictionary)","prefix":"","html_id":"Postgres.LoadTypes.pgLoadTypes"}]